Metadata-Version: 2.1
Name: pacoteMarcos
Version: 0.0.1
Summary: Pacote python para exibir número de 1 a 9
Home-page: https://github.com/marcos-de-sousa/pacoteMarcos
Author: Marcos Paulo Alves de Sousa
Author-email: desousa.mpa@gmail.com
License: MIT License
Keywords: Pacote
Platform: UNKNOWN
